sphinxjp.themes.basicstrap-0.5.0-py3.7-nspkg.pth
sphinxjp/themes/basicstrap/__init__.py
sphinxjp/themes/basicstrap/directives.py
sphinxjp/themes/basicstrap/templates/basicstrap/_theme_preview.html
sphinxjp/themes/basicstrap/templates/basicstrap/layout.html
sphinxjp/themes/basicstrap/templates/basicstrap/search.html
sphinxjp/themes/basicstrap/templates/basicstrap/searchbox.html
sphinxjp/themes/basicstrap/templates/basicstrap/searchresults.html
sphinxjp/themes/basicstrap/templates/basicstrap/theme.conf
sphinxjp/themes/basicstrap/templates/basicstrap/static/css/basicstrap-base.css
sphinxjp/themes/basicstrap/templates/basicstrap/static/css/basicstrap.css_t
sphinxjp/themes/basicstrap/templates/basicstrap/static/css/font-awesome-ie7.min.css
sphinxjp/themes/basicstrap/templates/basicstrap/static/css/font-awesome.min.css
sphinxjp/themes/basicstrap/templates/basicstrap/static/css/adjust_theme/_common_adjust.css
sphinxjp/themes/basicstrap/templates/basicstrap/static/css/adjust_theme/bootswatch-amelia.css_t
sphinxjp/themes/basicstrap/templates/basicstrap/static/css/adjust_theme/bootswatch-cerulean.css_t
sphinxjp/themes/basicstrap/templates/basicstrap/static/css/adjust_theme/bootswatch-cosmo.css_t
sphinxjp/themes/basicstrap/templates/basicstrap/static/css/adjust_theme/bootswatch-cyborg.css_t
sphinxjp/themes/basicstrap/templates/basicstrap/static/css/adjust_theme/bootswatch-darkly.css_t
sphinxjp/themes/basicstrap/templates/basicstrap/static/css/adjust_theme/bootswatch-flatly.css_t
sphinxjp/themes/basicstrap/templates/basicstrap/static/css/adjust_theme/bootswatch-journal.css_t
sphinxjp/themes/basicstrap/templates/basicstrap/static/css/adjust_theme/bootswatch-lumen.css_t
sphinxjp/themes/basicstrap/templates/basicstrap/static/css/adjust_theme/bootswatch-paper.css_t
sphinxjp/themes/basicstrap/templates/basicstrap/static/css/adjust_theme/bootswatch-readable.css_t
sphinxjp/themes/basicstrap/templates/basicstrap/static/css/adjust_theme/bootswatch-sandstone.css_t
sphinxjp.themes.basicstrap-0.5.0.dist-info/METADATA
sphinxjp.themes.basicstrap-0.5.0.dist-info/WHEEL
sphinxjp.themes.basicstrap-0.5.0.dist-info/entry_points.txt
sphinxjp.themes.basicstrap-0.5.0.dist-info/namespace_packages.txt
sphinxjp.themes.basicstrap-0.5.0.dist-info/top_level.txt
sphinxjp.themes.basicstrap-0.5.0.dist-info/RECORD
