Metadata-Version: 1.1
Name: sphinxjp.themes.basicstrap
Version: 0.5.0
Summary: A sphinx theme for Basicstrap style. Using Twitter Bootstrap. #sphinxjp
Home-page: https://github.com/tell-k/sphinxjp.themes.basicstrap
Author: tell-k
Author-email: ffk2005@gmail.com
License: MIT
Keywords: sphinx,reStructuredText,theme
Platform: UNKNOWN
Classifier: Development Status :: 4 - Beta
Classifier: License :: OSI Approved :: MIT License
Classifier: Programming Language :: Python
Classifier: Programming Language :: Python :: 3
Classifier: Programming Language :: Python :: 3.4
Classifier: Programming Language :: Python :: 3.5
Classifier: Programming Language :: Python :: 3.6
Classifier: Programming Language :: Python :: 3.7
Classifier: Framework :: Sphinx
Classifier: Framework :: Sphinx :: Extension
Classifier: Framework :: Sphinx :: Theme
Classifier: Topic :: Software Development
Classifier: Topic :: Software Development :: Documentation
Classifier: Topic :: Text Processing :: Markup
